vqubo/__init__.py
vqubo/vqubo.py
vqubo-0.0.1.dist-info/METADATA
vqubo-0.0.1.dist-info/RECORD
vqubo-0.0.1.dist-info/WHEEL
vqubo-0.0.1.dist-info/top_level.txt
