Metadata-Version: 2.1
Name: vqubo
Version: 0.0.1
Summary: QUBO matrix visualization tool
Home-page: https://github.com
Author: Yu Yamashiro
Author-email: y.yamashiro@j-ij.com
License: Apache License 2.0
Platform: UNKNOWN
Requires-Dist: matplotlib
